Workbook

Sheet README
A1: HealthLink EHR – Project Data Workbook (A2_GroupXX_ProjectData.xlsx)
A3: Tabs:
A4: Budget – task costs, BAC, contingency, and earned value inputs
A5: Dashboard – PV, EV, AC, SV, CV, SPI, CPI and RAG status at the status date
A6: Risks – risk register with scores; HeatMap – 5x5 heat map (counts per cell)
A7: Stakeholders – register with power/interest; CommsPlan – communication plan
A8: Quality – metrics and targets; ChangeLog – change requests; RACI – responsibility matrix
A9: IssueLog – issues and corrective actions
A10: Closure – closure checklist; Benefits – benefits realisation plan; Lessons – lessons learned so far

Sheet Budget
A1: Budget and Earned Value Inputs (status date 25 Sep 2026)
A3: WBS | B3: Task | C3: Duration (days) | D3: Resource 1 | E3: Resource 2 | F3: Combined rate ($/hr) | G3: Labour cost ($) | H3: Fixed cost ($) | I3: Total planned cost ($) | J3: Planned % complete at status date | K3: Actual % complete at status date | L3: Overrun days | M3: PV ($) | N3: EV ($) | O3: AC ($) | R3: Resource | S3: Rate ($/hr)
A4: 1.1 | B4: Project charter approved | C4: 5 | D4: Project Manager | F4: =IFERROR(INDEX($S$5:$S$14,MATCH(D4,$R$5:$R$14,0)),0)+IFERROR(INDEX($S$5:$S$14,MATCH(E4,$R$5:$R$14,0)),0) -> 120 | G4: =C4*$S$16*F4 -> 4800 | H4: 0 | I4: =G4+H4 -> 4800 | J4: 1 | K4: 1 | L4: 0 | M4: =I4*J4 -> 4800 | N4: =I4*K4 -> 4800 | O4: =I4*K4+L4*$S$16*F4 -> 4800
A5: 1.2 | B5: Stakeholder register & engagement plan | C5: 5 | D5: Business Analyst | E5: Project Manager | F5: =IFERROR(INDEX($S$5:$S$14,MATCH(D5,$R$5:$R$14,0)),0)+IFERROR(INDEX($S$5:$S$14,MATCH(E5,$R$5:$R$14,0)),0) -> 215 | G5: =C5*$S$16*F5 -> 8600 | H5: 0 | I5: =G5+H5 -> 8600 | J5: 1 | K5: 1 | L5: 0 | M5: =I5*J5 -> 8600 | N5: =I5*K5 -> 8600 | O5: =I5*K5+L5*$S$16*F5 -> 8600 | R5: Project Manager | S5: 120
A6: 1.3 | B6: PM plan & baseline | C6: 10 | D6: Project Manager | F6: =IFERROR(INDEX($S$5:$S$14,MATCH(D6,$R$5:$R$14,0)),0)+IFERROR(INDEX($S$5:$S$14,MATCH(E6,$R$5:$R$14,0)),0) -> 120 | G6: =C6*$S$16*F6 -> 9600 | H6: 0 | I6: =G6+H6 -> 9600 | J6: 1 | K6: 1 | L6: 0 | M6: =I6*J6 -> 9600 | N6: =I6*K6 -> 9600 | O6: =I6*K6+L6*$S$16*F6 -> 9600 | R6: Business Analyst | S6: 95
A7: 2.1 | B7: Clinical workflow analysis (3 sites) | C7: 15 | D7: Business Analyst | E7: Clinical Lead | F7: =IFERROR(INDEX($S$5:$S$14,MATCH(D7,$R$5:$R$14,0)),0)+IFERROR(INDEX($S$5:$S$14,MATCH(E7,$R$5:$R$14,0)),0) -> 205 | G7: =C7*$S$16*F7 -> 24600 | H7: 0 | I7: =G7+H7 -> 24600 | J7: 1 | K7: 1 | L7: 0 | M7: =I7*J7 -> 24600 | N7: =I7*K7 -> 24600 | O7: =I7*K7+L7*$S$16*F7 -> 24600 | R7: Clinical Lead | S7: 110
A8: 2.2 | B8: Requirements specification | C8: 15 | D8: Business Analyst | E8: Clinical Lead | F8: =IFERROR(INDEX($S$5:$S$14,MATCH(D8,$R$5:$R$14,0)),0)+IFERROR(INDEX($S$5:$S$14,MATCH(E8,$R$5:$R$14,0)),0) -> 205 | G8: =C8*$S$16*F8 -> 24600 | H8: 0 | I8: =G8+H8 -> 24600 | J8: 1 | K8: 1 | L8: 0 | M8: =I8*J8 -> 24600 | N8: =I8*K8 -> 24600 | O8: =I8*K8+L8*$S$16*F8 -> 24600 | R8: EHR Vendor Consultant | S8: 160
A9: 2.3 | B9: Vendor tender & selection (incl. EHR licences) | C9: 20 | D9: Business Analyst | E9: Project Manager | F9: =IFERROR(INDEX($S$5:$S$14,MATCH(D9,$R$5:$R$14,0)),0)+IFERROR(INDEX($S$5:$S$14,MATCH(E9,$R$5:$R$14,0)),0) -> 215 | G9: =C9*$S$16*F9 -> 34400 | H9: 2400000 | I9: =G9+H9 -> 2434400 | J9: 1 | K9: 1 | L9: 0 | M9: =I9*J9 -> 2434400 | N9: =I9*K9 -> 2434400 | O9: =I9*K9+L9*$S$16*F9 -> 2434400 | R9: Integration Developer | S9: 130
A10: 3.1 | B10: Network & hardware upgrade (incl. hardware) | C10: 30 | D10: Network/Infrastructure Engineer | F10: =IFERROR(INDEX($S$5:$S$14,MATCH(D10,$R$5:$R$14,0)),0)+IFERROR(INDEX($S$5:$S$14,MATCH(E10,$R$5:$R$14,0)),0) -> 105 | G10: =C10*$S$16*F10 -> 25200 | H10: 650000 | I10: =G10+H10 -> 675200 | J10: 1 | K10: 1 | L10: 0 | M10: =I10*J10 -> 675200 | N10: =I10*K10 -> 675200 | O10: =I10*K10+L10*$S$16*F10 -> 675200 | R10: Data Migration Specialist | S10: 115
A11: 3.2 | B11: EHR configuration & clinical templates | C11: 40 | D11: Clinical Lead | E11: EHR Vendor Consultant | F11: =IFERROR(INDEX($S$5:$S$14,MATCH(D11,$R$5:$R$14,0)),0)+IFERROR(INDEX($S$5:$S$14,MATCH(E11,$R$5:$R$14,0)),0) -> 270 | G11: =C11*$S$16*F11 -> 86400 | H11: 0 | I11: =G11+H11 -> 86400 | J11: 1 | K11: 1 | L11: 10 | M11: =I11*J11 -> 86400 | N11: =I11*K11 -> 86400 | O11: =I11*K11+L11*$S$16*F11 -> 108000 | R11: Network/Infrastructure Engineer | S11: 105
A12: 3.3 | B12: Integrations (pathology, radiology, pharmacy) | C12: 25 | D12: Integration Developer | F12: =IFERROR(INDEX($S$5:$S$14,MATCH(D12,$R$5:$R$14,0)),0)+IFERROR(INDEX($S$5:$S$14,MATCH(E12,$R$5:$R$14,0)),0) -> 130 | G12: =C12*$S$16*F12 -> 26000 | H12: 0 | I12: =G12+H12 -> 26000 | J12: 0.4 | K12: 0 | L12: 0 | M12: =I12*J12 -> 10400 | N12: =I12*K12 -> 0 | O12: =I12*K12+L12*$S$16*F12 -> 0 | R12: Security & Privacy Officer | S12: 115
A13: 3.4 | B13: Privacy & security controls | C13: 15 | D13: Security & Privacy Officer | F13: =IFERROR(INDEX($S$5:$S$14,MATCH(D13,$R$5:$R$14,0)),0)+IFERROR(INDEX($S$5:$S$14,MATCH(E13,$R$5:$R$14,0)),0) -> 115 | G13: =C13*$S$16*F13 -> 13800 | H13: 0 | I13: =G13+H13 -> 13800 | J13: 0.6667 | K13: 0 | L13: 0 | M13: =I13*J13 -> 9200.46 | N13: =I13*K13 -> 0 | O13: =I13*K13+L13*$S$16*F13 -> 0 | R13: Test Analyst | S13: 85
A14: 4.1 | B14: Legacy data cleansing & mapping | C14: 25 | D14: Business Analyst | E14: Data Migration Specialist | F14: =IFERROR(INDEX($S$5:$S$14,MATCH(D14,$R$5:$R$14,0)),0)+IFERROR(INDEX($S$5:$S$14,MATCH(E14,$R$5:$R$14,0)),0) -> 210 | G14: =C14*$S$16*F14 -> 42000 | H14: 0 | I14: =G14+H14 -> 42000 | J14: 1 | K14: 1 | L14: 0 | M14: =I14*J14 -> 42000 | N14: =I14*K14 -> 42000 | O14: =I14*K14+L14*$S$16*F14 -> 42000 | R14: Trainer | S14: 80
A15: 4.2 | B15: Test data migrations (2 cycles) | C15: 15 | D15: Data Migration Specialist | E15: Test Analyst | F15: =IFERROR(INDEX($S$5:$S$14,MATCH(D15,$R$5:$R$14,0)),0)+IFERROR(INDEX($S$5:$S$14,MATCH(E15,$R$5:$R$14,0)),0) -> 200 | G15: =C15*$S$16*F15 -> 24000 | H15: 0 | I15: =G15+H15 -> 24000 | J15: 0.6667 | K15: 0 | L15: 0 | M15: =I15*J15 -> 16000.8 | N15: =I15*K15 -> 0 | O15: =I15*K15+L15*$S$16*F15 -> 0
A16: 5.1 | B16: System & integration testing | C16: 15 | D16: Integration Developer | E16: Test Analyst | F16: =IFERROR(INDEX($S$5:$S$14,MATCH(D16,$R$5:$R$14,0)),0)+IFERROR(INDEX($S$5:$S$14,MATCH(E16,$R$5:$R$14,0)),0) -> 215 | G16: =C16*$S$16*F16 -> 25800 | H16: 0 | I16: =G16+H16 -> 25800 | J16: 0 | K16: 0 | L16: 0 | M16: =I16*J16 -> 0 | N16: =I16*K16 -> 0 | O16: =I16*K16+L16*$S$16*F16 -> 0 | R16: Hours per day | S16: 8
A17: 5.2 | B17: User acceptance testing | C17: 10 | D17: Clinical Lead | E17: Test Analyst | F17: =IFERROR(INDEX($S$5:$S$14,MATCH(D17,$R$5:$R$14,0)),0)+IFERROR(INDEX($S$5:$S$14,MATCH(E17,$R$5:$R$14,0)),0) -> 195 | G17: =C17*$S$16*F17 -> 15600 | H17: 0 | I17: =G17+H17 -> 15600 | J17: 0 | K17: 0 | L17: 0 | M17: =I17*J17 -> 0 | N17: =I17*K17 -> 0 | O17: =I17*K17+L17*$S$16*F17 -> 0
A18: 6.1 | B18: Training materials & super-users | C18: 20 | D18: Clinical Lead | E18: Trainer | F18: =IFERROR(INDEX($S$5:$S$14,MATCH(D18,$R$5:$R$14,0)),0)+IFERROR(INDEX($S$5:$S$14,MATCH(E18,$R$5:$R$14,0)),0) -> 190 | G18: =C18*$S$16*F18 -> 30400 | H18: 0 | I18: =G18+H18 -> 30400 | J18: 0.5 | K18: 0 | L18: 0 | M18: =I18*J18 -> 15200 | N18: =I18*K18 -> 0 | O18: =I18*K18+L18*$S$16*F18 -> 0
A19: 6.2 | B19: End-user training (all sites) | C19: 20 | D19: Trainer | F19: =IFERROR(INDEX($S$5:$S$14,MATCH(D19,$R$5:$R$14,0)),0)+IFERROR(INDEX($S$5:$S$14,MATCH(E19,$R$5:$R$14,0)),0) -> 80 | G19: =C19*$S$16*F19 -> 12800 | H19: 0 | I19: =G19+H19 -> 12800 | J19: 0 | K19: 0 | L19: 0 | M19: =I19*J19 -> 0 | N19: =I19*K19 -> 0 | O19: =I19*K19+L19*$S$16*F19 -> 0
A20: 7.1 | B20: Pilot go-live: Site A | C20: 5 | D20: Clinical Lead | E20: Project Manager | F20: =IFERROR(INDEX($S$5:$S$14,MATCH(D20,$R$5:$R$14,0)),0)+IFERROR(INDEX($S$5:$S$14,MATCH(E20,$R$5:$R$14,0)),0) -> 230 | G20: =C20*$S$16*F20 -> 9200 | H20: 0 | I20: =G20+H20 -> 9200 | J20: 0 | K20: 0 | L20: 0 | M20: =I20*J20 -> 0 | N20: =I20*K20 -> 0 | O20: =I20*K20+L20*$S$16*F20 -> 0
A21: 7.2 | B21: Post-pilot review & fixes | C21: 10 | D21: Integration Developer | E21: Project Manager | F21: =IFERROR(INDEX($S$5:$S$14,MATCH(D21,$R$5:$R$14,0)),0)+IFERROR(INDEX($S$5:$S$14,MATCH(E21,$R$5:$R$14,0)),0) -> 250 | G21: =C21*$S$16*F21 -> 20000 | H21: 0 | I21: =G21+H21 -> 20000 | J21: 0 | K21: 0 | L21: 0 | M21: =I21*J21 -> 0 | N21: =I21*K21 -> 0 | O21: =I21*K21+L21*$S$16*F21 -> 0
A22: 7.3 | B22: Rollout Sites B & C + final migration | C22: 10 | D22: Clinical Lead | E22: Project Manager | F22: =IFERROR(INDEX($S$5:$S$14,MATCH(D22,$R$5:$R$14,0)),0)+IFERROR(INDEX($S$5:$S$14,MATCH(E22,$R$5:$R$14,0)),0) -> 230 | G22: =C22*$S$16*F22 -> 18400 | H22: 0 | I22: =G22+H22 -> 18400 | J22: 0 | K22: 0 | L22: 0 | M22: =I22*J22 -> 0 | N22: =I22*K22 -> 0 | O22: =I22*K22+L22*$S$16*F22 -> 0
A23: 8.1 | B23: Hypercare support | C23: 20 | D23: Clinical Lead | E23: Test Analyst | F23: =IFERROR(INDEX($S$5:$S$14,MATCH(D23,$R$5:$R$14,0)),0)+IFERROR(INDEX($S$5:$S$14,MATCH(E23,$R$5:$R$14,0)),0) -> 195 | G23: =C23*$S$16*F23 -> 31200 | H23: 0 | I23: =G23+H23 -> 31200 | J23: 0 | K23: 0 | L23: 0 | M23: =I23*J23 -> 0 | N23: =I23*K23 -> 0 | O23: =I23*K23+L23*$S$16*F23 -> 0
A24: 8.2 | B24: Legacy decommissioning | C24: 10 | D24: Network/Infrastructure Engineer | F24: =IFERROR(INDEX($S$5:$S$14,MATCH(D24,$R$5:$R$14,0)),0)+IFERROR(INDEX($S$5:$S$14,MATCH(E24,$R$5:$R$14,0)),0) -> 105 | G24: =C24*$S$16*F24 -> 8400 | H24: 0 | I24: =G24+H24 -> 8400 | J24: 0 | K24: 0 | L24: 0 | M24: =I24*J24 -> 0 | N24: =I24*K24 -> 0 | O24: =I24*K24+L24*$S$16*F24 -> 0
A25: 8.3 | B25: Closure, lessons learned & benefits handover | C25: 5 | D25: Project Manager | F25: =IFERROR(INDEX($S$5:$S$14,MATCH(D25,$R$5:$R$14,0)),0)+IFERROR(INDEX($S$5:$S$14,MATCH(E25,$R$5:$R$14,0)),0) -> 120 | G25: =C25*$S$16*F25 -> 4800 | H25: 0 | I25: =G25+H25 -> 4800 | J25: 0 | K25: 0 | L25: 0 | M25: =I25*J25 -> 0 | N25: =I25*K25 -> 0 | O25: =I25*K25+L25*$S$16*F25 -> 0
B26: TOTAL (BAC = Budget at Completion) | G26: =SUM(G4:G25) -> 500600 | H26: =SUM(H4:H25) -> 3050000 | I26: =SUM(I4:I25) -> 3550600 | M26: =SUM(M4:M25) -> 3361001.3 | N26: =SUM(N4:N25) -> 3310200 | O26: =SUM(O4:O25) -> 3331800
B27: Contingency reserve % | I27: 0.1
B28: Contingency reserve ($) | I28: =I26*I27 -> 355060
B29: Approved project budget ($) | I29: =I26+I28 -> 3905660
B31: Notes: Planned % = share of task duration that should be finished by 25 Sep 2026 per the baseline. 3.2 finished 10 working days late (Overrun days = 10), so 3.3, 3.4, 4.2 and 6.1 had not started.

Sheet Dashboard
A1: Project Status Dashboard – status date Fri 25 Sep 2026
A3: Measure | B3: Value | C3: What it means
A4: Budget at Completion (BAC) | B4: =Budget!I26 -> 3550600 | C4: Total planned cost of the project (from ProjectLibre costs)
A5: Planned Value (PV) | B5: =Budget!M26 -> 3361001.3 | C5: Value of work that should be done by 25 Sep
A6: Earned Value (EV) | B6: =Budget!N26 -> 3310200 | C6: Value of work actually done by 25 Sep
A7: Actual Cost (AC) | B7: =Budget!O26 -> 3331800 | C7: What the completed work actually cost
A8: Schedule Variance SV = EV − PV | B8: =B6-B5 -> -50801.26 | C8: Negative = behind schedule
A9: Cost Variance CV = EV − AC | B9: =B6-B7 -> -21600 | C9: Negative = over budget
A10: Schedule Performance Index SPI = EV / PV | B10: =IFERROR(B6/B5,0) -> 0.98488508 | C10: Below 1.00 = behind schedule
A11: Cost Performance Index CPI = EV / AC | B11: =IFERROR(B6/B7,0) -> 0.99351702 | C11: Below 1.00 = over budget
A12: Estimate at Completion EAC = BAC / CPI | B12: =IFERROR(B4/B11,0) -> 3573768.7 | C12: Forecast final cost if current cost performance continues
A13: Variance at Completion VAC = BAC − EAC | B13: =B4-B12 -> -23168.679 | C13: Forecast over/under run at completion
A14: Critical path slip (working days, from ProjectLibre) | B14: 10 | C14: 3.2 finished 10 days late and is on the critical path
A15: Days recovered by CR-02 (forecast) | B15: 5 | C15: Second vendor consultant on 3.3 (approved change CR-02)
A16: Forecast go-live slip (working days) | B16: =B14-B15 -> 5 | C16: Remaining delay to go-live forecast
A17: Schedule RAG | B17: =IF(OR(B10<0.95,B16>10),"RED",IF(OR(B10<1,B16>0),"AMBER","GREEN")) -> AMBER | C17: Rule: RED if SPI<0.95 or slip>10 days; AMBER if SPI<1 or any slip
A18: Cost RAG | B18: =IF(B11<0.95,"RED",IF(B11<1,"AMBER","GREEN")) -> AMBER | C18: Rule: RED if CPI<0.95; AMBER if CPI<1
A20: Interpretation: SPI and CPI look close to 1.00 because the large fixed costs (licences, hardware) were already spent on time. The real problem is the critical path: 3.2 finished 10 days late, which pushes go-live back unless corrected. Look at the slip in days, not just the indices.

Sheet Risks
A1: Risk Register
A3: ID | B3: Risk (cause → event → effect) | C3: Category | D3: Likelihood (1–5) | E3: Impact (1–5) | F3: Score (L×I) | G3: Rating | H3: Owner | I3: Response type | J3: Response action | K3: Linked WBS | L3: Trigger / early warning | M3: Status
A4: R01 | B4: Legacy data is incomplete or duplicated, so migrated records are wrong and patient safety is at risk | C4: Data | D4: 4 | E4: 5 | F4: =D4*E4 -> 20 | G4: =IF(F4>=15,"High",IF(F4>=8,"Medium","Low")) -> High | H4: Data Migration Specialist | I4: Mitigate | J4: Cleansing rules, 2 test migrations, clinician sample audit (≥99.5% accuracy) | K4: 4.1, 4.2 | L4: Test migration accuracy below 99.5% | M4: Open
A5: R02 | B5: Clinicians resist the new workflow, so adoption is low after go-live | C5: People | D5: 4 | E5: 4 | F5: =D5*E5 -> 16 | G5: =IF(F5>=15,"High",IF(F5>=8,"Medium","Low")) -> High | H5: Clinical Lead | I5: Mitigate | J5: Clinician super-users, involve clinicians in UAT, targeted training | K5: 6.1, 6.2 | L5: Low training attendance; negative UAT feedback | M5: Open
A6: R03 | B6: EHR configuration takes longer than planned, delaying go-live (critical path) | C6: Schedule | D6: 3 | E6: 5 | F6: =D6*E6 -> 15 | G6: =IF(F6>=15,"High",IF(F6>=8,"Medium","Low")) -> High | H6: Project Manager | I6: Mitigate | J6: Fixed-scope sprints, weekly progress review, vendor penalty clauses | K6: 3.2 | L6: Config sprint misses its target | M6: Triggered – see ISSUE-01
A7: R04 | B7: Integration with pathology/radiology/pharmacy fails, so results don't reach clinicians | C7: Technical | D7: 3 | E7: 5 | F7: =D7*E7 -> 15 | G7: =IF(F7>=15,"High",IF(F7>=8,"Medium","Low")) -> High | H7: Integration Developer | I7: Mitigate | J7: Early interface testing, HL7/FHIR standards, vendor support | K7: 3.3 | L7: Interface test failures | M7: Open
A8: R05 | B8: Privacy breach or unauthorised access to patient records | C8: Compliance | D8: 2 | E8: 5 | F8: =D8*E8 -> 10 | G8: =IF(F8>=15,"High",IF(F8>=8,"Medium","Low")) -> Medium | H8: Security & Privacy Officer | I8: Avoid | J8: Role-based access, audit logs, encryption, privacy impact assessment | K8: 3.4 | L8: Audit log anomalies | M8: Open
A9: R06 | B9: Cutover downtime interrupts clinical care | C9: Operational | D9: 3 | E9: 5 | F9: =D9*E9 -> 15 | G9: =IF(F9>=15,"High",IF(F9>=8,"Medium","Low")) -> High | H9: Project Manager | I9: Mitigate | J9: Overnight cutover, paper downtime procedures, rollback plan | K9: 7.1, 7.3 | L9: Cutover rehearsal overruns | M9: Open
A10: R07 | B10: Vendor tender takes longer due to procurement rules | C10: Procurement | D10: 3 | E10: 3 | F10: =D10*E10 -> 9 | G10: =IF(F10>=15,"High",IF(F10>=8,"Medium","Low")) -> Medium | H10: Business Analyst | I10: Mitigate | J10: Early market scan, pre-approved evaluation criteria | K10: 2.3 | L10: Tender clarifications extend deadline | M10: Closed
A11: R08 | B11: Staff can't be released for training because of rostering | C11: People | D11: 4 | E11: 3 | F11: =D11*E11 -> 12 | G11: =IF(F11>=15,"High",IF(F11>=8,"Medium","Low")) -> Medium | H11: Trainer | I11: Mitigate | J11: Short modules, training across shifts, backfill budget | K11: 6.2 | L11: Booked sessions under 80% full | M11: Open
A12: R09 | B12: Hardware or network delivery delayed at smaller sites | C12: Supply | D12: 2 | E12: 3 | F12: =D12*E12 -> 6 | G12: =IF(F12>=15,"High",IF(F12>=8,"Medium","Low")) -> Low | H12: Network/Infrastructure Engineer | I12: Accept | J12: Monitor; 35 days float on 3.1; order early | K12: 3.1 | L12: Supplier delivery notice slips | M12: Closed
A13: R10 | B13: Cost overrun from change requests and scope creep | C13: Cost | D13: 3 | E13: 4 | F13: =D13*E13 -> 12 | G13: =IF(F13>=15,"High",IF(F13>=8,"Medium","Low")) -> Medium | H13: Project Sponsor | I13: Mitigate | J13: Change Control Board, 10% contingency reserve | K13: All | L13: CPI below 0.95 | M13: Open
A14: R11 | B14: Key vendor consultant leaves mid-project | C14: People | D14: 2 | E14: 4 | F14: =D14*E14 -> 8 | G14: =IF(F14>=15,"High",IF(F14>=8,"Medium","Low")) -> Medium | H14: Project Manager | I14: Transfer | J14: Contract requires vendor replacement within 10 days | K14: 3.2, 3.3 | L14: Consultant resignation notice | M14: Open
A15: R12 | B15: Legacy vendor support ends before decommissioning is complete | C15: Technical | D15: 2 | E15: 4 | F15: =D15*E15 -> 8 | G15: =IF(F15>=15,"High",IF(F15>=8,"Medium","Low")) -> Medium | H15: IT Operations Manager | I15: Mitigate | J15: Negotiate short support extension as fallback | K15: 8.2 | L15: Go-live slips past Feb 2027 | M15: Open
A17: Scoring: Likelihood 1 rare … 5 almost certain; Impact 1 negligible … 5 severe (patient safety, go-live, or >10% budget). Rating: High ≥15, Medium 8–14, Low ≤7.

Sheet HeatMap
A1: 5×5 Risk Heat Map (number of risks in each cell)
A3: Likelihood ↓ / Impact → | B3: 1 | C3: 2 | D3: 3 | E3: 4 | F3: 5
A4: 5 | B4: =COUNTIFS(Risks!$D$4:$D$15,$A4,Risks!$E$4:$E$15,B$3) -> 0 | C4: =COUNTIFS(Risks!$D$4:$D$15,$A4,Risks!$E$4:$E$15,C$3) -> 0 | D4: =COUNTIFS(Risks!$D$4:$D$15,$A4,Risks!$E$4:$E$15,D$3) -> 0 | E4: =COUNTIFS(Risks!$D$4:$D$15,$A4,Risks!$E$4:$E$15,E$3) -> 0 | F4: =COUNTIFS(Risks!$D$4:$D$15,$A4,Risks!$E$4:$E$15,F$3) -> 0
A5: 4 | B5: =COUNTIFS(Risks!$D$4:$D$15,$A5,Risks!$E$4:$E$15,B$3) -> 0 | C5: =COUNTIFS(Risks!$D$4:$D$15,$A5,Risks!$E$4:$E$15,C$3) -> 0 | D5: =COUNTIFS(Risks!$D$4:$D$15,$A5,Risks!$E$4:$E$15,D$3) -> 1 | E5: =COUNTIFS(Risks!$D$4:$D$15,$A5,Risks!$E$4:$E$15,E$3) -> 1 | F5: =COUNTIFS(Risks!$D$4:$D$15,$A5,Risks!$E$4:$E$15,F$3) -> 1
A6: 3 | B6: =COUNTIFS(Risks!$D$4:$D$15,$A6,Risks!$E$4:$E$15,B$3) -> 0 | C6: =COUNTIFS(Risks!$D$4:$D$15,$A6,Risks!$E$4:$E$15,C$3) -> 0 | D6: =COUNTIFS(Risks!$D$4:$D$15,$A6,Risks!$E$4:$E$15,D$3) -> 1 | E6: =COUNTIFS(Risks!$D$4:$D$15,$A6,Risks!$E$4:$E$15,E$3) -> 1 | F6: =COUNTIFS(Risks!$D$4:$D$15,$A6,Risks!$E$4:$E$15,F$3) -> 3
A7: 2 | B7: =COUNTIFS(Risks!$D$4:$D$15,$A7,Risks!$E$4:$E$15,B$3) -> 0 | C7: =COUNTIFS(Risks!$D$4:$D$15,$A7,Risks!$E$4:$E$15,C$3) -> 0 | D7: =COUNTIFS(Risks!$D$4:$D$15,$A7,Risks!$E$4:$E$15,D$3) -> 1 | E7: =COUNTIFS(Risks!$D$4:$D$15,$A7,Risks!$E$4:$E$15,E$3) -> 2 | F7: =COUNTIFS(Risks!$D$4:$D$15,$A7,Risks!$E$4:$E$15,F$3) -> 1
A8: 1 | B8: =COUNTIFS(Risks!$D$4:$D$15,$A8,Risks!$E$4:$E$15,B$3) -> 0 | C8: =COUNTIFS(Risks!$D$4:$D$15,$A8,Risks!$E$4:$E$15,C$3) -> 0 | D8: =COUNTIFS(Risks!$D$4:$D$15,$A8,Risks!$E$4:$E$15,D$3) -> 0 | E8: =COUNTIFS(Risks!$D$4:$D$15,$A8,Risks!$E$4:$E$15,E$3) -> 0 | F8: =COUNTIFS(Risks!$D$4:$D$15,$A8,Risks!$E$4:$E$15,F$3) -> 0
A10: Risk IDs by cell (for labelling the website image):
A11: L4 × I5 = 20 | B11: R01
A12: L4 × I4 = 16 | B12: R02
A13: L3 × I5 = 15 | B13: R03, R04, R06
A14: L4 × I3 = 12 | B14: R08
A15: L3 × I4 = 12 | B15: R10
A16: L2 × I5 = 10 | B16: R05
A17: L3 × I3 = 9 | B17: R07
A18: L2 × I4 = 8 | B18: R11, R12
A19: L2 × I3 = 6 | B19: R09
A21: Legend: red = High (15–25), amber = Medium (8–14), green = Low (1–7)

Sheet Stakeholders
A1: Stakeholder Register
A3: ID | B3: Stakeholder | C3: Role / interest in project | D3: Power | E3: Interest | F3: Current engagement | G3: Desired engagement | H3: Strategy (power-interest quadrant) | I3: Engagement actions
A4: S01 | B4: Network Chief Executive | C4: Project sponsor | D4: High | E4: High | F4: Supportive | G4: Leading | H4: Manage closely | I4: Monthly steering committee; approves budget and go-live
A5: S02 | B5: Chief Medical Information Officer | C5: Business owner / clinical sponsor | D5: High | E5: High | F5: Supportive | G5: Leading | H5: Manage closely | I5: Chairs clinical design authority; signs off UAT
A6: S03 | B6: Doctors (all sites) | C6: End users | D6: Medium | E6: High | F6: Resistant | G6: Supportive | H6: Keep informed → involve | I6: Clinician champions, UAT involvement, demos
A7: S04 | B7: Nurses & Nurse Unit Managers | C7: End users; release staff for training | D7: Medium | E7: High | F7: Neutral | G7: Supportive | H7: Manage closely | I7: Roster-friendly training, super-users on each ward
A8: S05 | B8: Health Information / Records team | C8: Data owners | D8: Medium | E8: High | F8: Neutral | G8: Supportive | H8: Keep informed | I8: Data migration working group
A9: S06 | B9: IT Operations Manager | C9: Runs infrastructure after handover | D9: High | E9: Medium | F9: Supportive | G9: Supportive | H9: Keep satisfied | I9: Technical working group; BAU handover plan
A10: S07 | B10: EHR Vendor | C10: Supplier | D10: High | E10: Medium | F10: Supportive | G10: Supportive | H10: Keep satisfied | I10: Contract meetings, weekly delivery review
A11: S08 | B11: Privacy Commissioner / State Health Dept | C11: Regulator | D11: High | E11: Low | F11: Unaware | G11: Neutral | H11: Keep satisfied | I11: Privacy impact assessment shared; compliance reports
A12: S09 | B12: Patients & community | C12: Affected by record accuracy and downtime | D12: Low | E12: High | F12: Unaware | G12: Neutral | H12: Keep informed | I12: Hospital newsletter, signage during cutover
A13: S10 | B13: Finance Director | C13: Budget control | D13: High | E13: Low | F13: Neutral | G13: Supportive | H13: Keep satisfied | I13: Monthly cost report (CPI, contingency)
A14: S11 | B14: Pathology, radiology & pharmacy departments | C14: Integration partners | D14: Medium | E14: Medium | F14: Neutral | G14: Supportive | H14: Keep informed | I14: Interface testing sessions

Sheet CommsPlan
A1: Communication Plan
A3: Communication | B3: Audience | C3: Content | D3: Method | E3: Frequency | F3: Owner
A4: Steering committee report | B4: Sponsor, CMIO, Finance Director | C4: Status, RAG, SPI/CPI, top risks, decisions needed | D4: Meeting + written report | E4: Monthly | F4: Project Manager
A5: Clinical design authority | B5: CMIO, clinician champions | C5: Configuration decisions, template sign-off | D5: Workshop | E5: Fortnightly | F5: Clinical Lead
A6: Project team stand-up | B6: Project team, vendor | C6: Progress, blockers, Trello board review | D6: Video call | E6: Daily (15 min) | F6: Project Manager
A7: Change Control Board | B7: Sponsor, CMIO, IT Ops Manager | C7: Change requests and impact | D7: Meeting | E7: Fortnightly / as needed | F7: Project Manager
A8: Staff newsletter & intranet | B8: All staff | C8: What's changing, training dates, go-live dates | D8: Email / intranet | E8: Fortnightly | F8: Trainer
A9: Ward huddles | B9: Nurses, doctors | C9: Training reminders, go-live readiness, quick tips | D9: Face to face | E9: Weekly before go-live | F9: Super-users
A10: Vendor delivery review | B10: EHR Vendor | C10: Deliverables, defects, contract milestones | D10: Meeting | E10: Weekly | F10: Project Manager
A11: Regulator compliance update | B11: Privacy Commissioner / State Health Dept | C11: Privacy impact assessment, security controls | D11: Formal letter / report | E11: At milestones M2 and M3 | F11: Security & Privacy Officer
A12: Patient notices | B12: Patients & community | C12: Downtime periods, what to expect | D12: Signage, website | E12: 2 weeks before each site go-live | F12: Communications Officer

Sheet Quality
A1: Quality Requirements and Metrics
A3: ID | B3: Quality requirement | C3: Metric | D3: Target | E3: How / when checked (quality control) | F3: Linked WBS | G3: Owner
A4: Q1 | B4: Data migration accuracy | C4: % of sampled records matching source | D4: ≥ 99.5% | E4: Sample audit of 500 records per test cycle | F4: 4.2, 7.3 | G4: Data Migration Specialist
A5: Q2 | B5: Critical defects at go-live | C5: Open severity-1 defects | D5: 0 | E5: Defect log review at readiness sign-off (M3) | F5: 5.1, 5.2 | G5: Test Analyst
A6: Q3 | B6: UAT pass rate | C6: % of UAT scripts passed | D6: ≥ 95% | E6: UAT results report | F6: 5.2 | G6: Clinical Lead
A7: Q4 | B7: Staff trained before go-live | C7: % of staff completing training | D7: ≥ 95% | E7: Training attendance records | F7: 6.2 | G7: Trainer
A8: Q5 | B8: System availability | C8: Uptime during hypercare | D8: ≥ 99.9% | E8: Vendor monitoring report | F8: 8.1 | G8: IT Operations Manager
A9: Q6 | B9: Record retrieval time | C9: Time to open full cross-site record | D9: < 2 minutes | E9: Timed sample, 3 months after go-live | F9: Benefit B1 | G9: Clinical Lead

Sheet ChangeLog
A1: Change Request Log
A3: CR ID | B3: Date raised | C3: Raised by | D3: Change requested | E3: Impact (scope / time / cost) | F3: Risk impact | G3: Decision | H3: Decided by / date
A4: CR-01 | B4: 14 Aug 2026 | C4: CMIO | D4: Add radiology image viewer to clinician workspace | E4: Scope +; +5 days on 3.3 (non-critical at the time); +$12,000 | F4: Low (uses existing interface) | G4: Approved | H4: CCB 21 Aug 2026
A5: CR-02 | B5: 18 Sep 2026 | C5: Project Manager | D5: Add second vendor consultant to 3.3 Integrations to recover 5 of 10 days lost on 3.2 | E5: Schedule −5 days; cost +$25,600 (20 days × 8 h × $160) from contingency | F5: Reduces R03/R04 exposure | G5: Approved | H5: CCB 22 Sep 2026
A6: CR-03 | B6: 21 Sep 2026 | C6: Site B Director | D6: Add patient-facing mobile app | E6: Out of scope (exclusion); est. +$400,000 and +60 days | F6: High | G6: Rejected – refer to future project | H6: CCB 22 Sep 2026

Sheet RACI
A1: RACI Matrix (R = Responsible, A = Accountable, C = Consulted, I = Informed)
A3: Deliverable | B3: Sponsor | C3: CMIO | D3: Project Manager | E3: Business Analyst | F3: Clinical Lead | G3: EHR Vendor | H3: IT Ops / Infrastructure | I3: Security & Privacy Officer | J3: Trainer
A4: Project charter | B4: A | C4: C | D4: R | E4: C | F4: C | G4: I | H4: I | I4: I | J4: I
A5: Requirements specification | B5: I | C5: A | D5: C | E5: R | F5: R | G5: C | H5: C | I5: C | J5: I
A6: Vendor selection | B6: A | C6: C | D6: R | E6: R | F6: C | G6: I | H6: C | I6: C | J6: I
A7: EHR configuration | B7: I | C7: A | D7: C | E7: C | F7: R | G7: R | H7: I | I7: C | J7: I
A8: Integrations | B8: I | C8: C | D8: A | E8: C | F8: C | G8: R | H8: R | I8: C | J8: I
A9: Data migration | B9: I | C9: C | D9: A | E9: R | F9: C | G9: R | H9: C | I9: C | J9: I
A10: Privacy & security controls | B10: I | C10: C | D10: A | E10: I | F10: I | G10: C | H10: C | I10: R | J10: I
A11: Testing & UAT | B11: I | C11: A | D11: C | E11: C | F11: R | G11: R | H11: C | I11: C | J11: I
A12: Training | B12: I | C12: C | D12: A | E12: I | F12: C | G12: C | H12: I | I12: I | J12: R
A13: Go-live decision | B13: A | C13: R | D13: R | E13: I | F13: C | G13: C | H13: C | I13: C | J13: I
A14: Project closure | B14: A | C14: C | D14: R | E14: C | F14: C | G14: I | H14: C | I14: I | J14: I
A16: Rule check: each deliverable has exactly one A.

Sheet IssueLog
A1: Issue Log
A3: ID | B3: Date raised | C3: Issue | D3: Priority | E3: Impact | F3: Owner | G3: Corrective action | H3: Status
A4: ISSUE-01 | B4: 11 Sep 2026 | C4: 3.2 EHR configuration not complete: clinicians requested template rework | D4: High | E4: Critical path slips 10 working days; go-live at risk | F4: Project Manager | G4: CR-02 approved: second vendor consultant on 3.3; start 6.1 in parallel with 3.3 | H4: Resolved 25 Sep 2026 (3.2 complete, 10 days late); schedule recovery in progress
A5: ISSUE-02 | B5: 29 Sep 2026 | C5: Pharmacy system vendor late supplying interface specification | D5: Medium | E5: Part of 3.3 blocked; could erode the 5 days recovered | F5: Integration Developer | G5: Escalated to vendor account manager; build pathology and radiology interfaces first | H5: Open – due 6 Oct 2026
A6: ISSUE-03 | B6: 22 Sep 2026 | C6: Site C training room unavailable in November | D6: Low | E6: 6.2 training at Site C may slip | F6: Trainer | G6: Book community clinic room; add online modules | H6: Open

Sheet Closure
A1: Project Closure Checklist
A3: Closure item | B3: Owner | C3: Status
A4: Sponsor acceptance of all deliverables | B4: Sponsor | C4: Planned
A5: All sites live and stable (M4) | B5: Project Manager | C5: Planned
A6: Hypercare exit criteria met | B6: IT Operations Manager | C6: Planned
A7: Open defects handed to BAU support | B7: IT Operations Manager | C7: Planned
A8: Legacy systems decommissioned and data archived | B8: IT Operations Manager | C8: Planned
A9: Vendor contract deliverables confirmed and final payment | B9: Finance Director | C9: Planned
A10: Final cost report and contingency reconciled | B10: Project Manager | C10: Planned
A11: Lessons learned workshop held and recorded | B11: Project Manager | C11: Planned
A12: Benefits owners confirmed and measurement scheduled | B12: Sponsor | C12: Planned
A13: Project documents archived | B13: Project Manager | C13: Planned
A14: Team released and thanked | B14: Project Manager | C14: Planned

Sheet Benefits
A1: Benefits Realisation Plan
A3: ID | B3: Benefit | C3: Measure | D3: Baseline | E3: Target | F3: When measured | G3: Benefit owner
A4: B1 | B4: Faster access to full patient records | C4: Time to retrieve cross-site record | D4: ~20 min | E4: < 2 min | F4: 3 months after go-live | G4: CMIO
A5: B2 | B5: Fewer medication errors from missing information | C5: Medication incidents per 1,000 admissions | D5: Baseline FY2026 | E5: −20% | F5: 12 months after go-live | G5: Director of Pharmacy
A6: B3 | B6: Less duplicate testing | C6: Repeat pathology tests within 48 h | D6: Baseline FY2026 | E6: −15% | F6: 12 months after go-live | G6: Pathology Director
A7: B4 | B7: Lower legacy support costs | C7: Annual support and licence cost of old systems | D7: 4 systems | E7: Decommissioned | F7: After 8.2 | G7: IT Operations Manager
A8: B5 | B8: Better compliance and audit | C8: Records with complete audit trail | D8: Partial | E8: 100% | F8: At go-live | G8: Security & Privacy Officer

Sheet Lessons
A1: Lessons Learned (to date)
A3: Area | B3: What happened | C3: Recommendation for future projects
A4: Clinical involvement | B4: Template rework on 3.2 happened because clinicians reviewed designs late | C4: Hold clinician review at the end of every configuration sprint, not only at the end
A5: Critical path focus | B5: SPI/CPI looked healthy while the critical path slipped | C5: Report critical-path slip in days alongside SPI/CPI on the dashboard
A6: Change control | B6: CR-03 (mobile app) was assessed and rejected quickly because exclusions were written in the scope statement | C6: Keep exclusions explicit in every scope document
A7: Vendor dependencies | B7: Third-party pharmacy vendor was not in the communication plan early enough (ISSUE-02) | C7: Add all integration partners to the stakeholder register at initiation
A8: Tool integration | B8: Using the same WBS codes in ProjectLibre, Trello and the risk register made tracing issues fast | C8: Set a WBS coding standard on day 1
